ImobilebbsSlickJiaocheng/README.md
ImobilebbsSlickJiaocheng/__init__.py
ImobilebbsSlickJiaocheng/__main__.py
ImobilebbsSlickJiaocheng/file.epub
ImobilebbsSlickJiaocheng/index.html
ImobilebbsSlickJiaocheng/css/__init__.py
ImobilebbsSlickJiaocheng/css/annotations.css
ImobilebbsSlickJiaocheng/css/main.css
ImobilebbsSlickJiaocheng/css/normalize.css
ImobilebbsSlickJiaocheng/css/popup.css
ImobilebbsSlickJiaocheng/font/__init__.py
ImobilebbsSlickJiaocheng/font/fontello.eot
ImobilebbsSlickJiaocheng/font/fontello.svg
ImobilebbsSlickJiaocheng/font/fontello.ttf
ImobilebbsSlickJiaocheng/font/fontello.woff
ImobilebbsSlickJiaocheng/img/__init__.py
ImobilebbsSlickJiaocheng/img/annotator-glyph-sprite.png
ImobilebbsSlickJiaocheng/img/annotator-icon-sprite.png
ImobilebbsSlickJiaocheng/img/apple-touch-icon.png
ImobilebbsSlickJiaocheng/img/cancelfullscreen.png
ImobilebbsSlickJiaocheng/img/close.png
ImobilebbsSlickJiaocheng/img/fullscreen.png
ImobilebbsSlickJiaocheng/img/loader.gif
ImobilebbsSlickJiaocheng/img/menu-icon.png
ImobilebbsSlickJiaocheng/img/save.png
ImobilebbsSlickJiaocheng/img/saved.png
ImobilebbsSlickJiaocheng/img/settings-s.png
ImobilebbsSlickJiaocheng/img/settings.png
ImobilebbsSlickJiaocheng/img/star.png
ImobilebbsSlickJiaocheng/js/__init__.py
ImobilebbsSlickJiaocheng/js/epub.js
ImobilebbsSlickJiaocheng/js/epub.min.js
ImobilebbsSlickJiaocheng/js/epub.min.map
ImobilebbsSlickJiaocheng/js/hooks.min.js
ImobilebbsSlickJiaocheng/js/hooks.min.map
ImobilebbsSlickJiaocheng/js/reader.js
ImobilebbsSlickJiaocheng/js/reader.js.map
ImobilebbsSlickJiaocheng/js/reader.min.js
ImobilebbsSlickJiaocheng/js/reader.min.map
ImobilebbsSlickJiaocheng/js/hooks/__init__.py
ImobilebbsSlickJiaocheng/js/hooks/extensions/__init__.py
ImobilebbsSlickJiaocheng/js/hooks/extensions/highlight.js
ImobilebbsSlickJiaocheng/js/libs/__init__.py
ImobilebbsSlickJiaocheng/js/libs/jquery.min.js
ImobilebbsSlickJiaocheng/js/libs/localforage.min.js
ImobilebbsSlickJiaocheng/js/libs/screenfull.js
imobilebbs_slick_jiaocheng-2024.3.2.0.dist-info/METADATA
imobilebbs_slick_jiaocheng-2024.3.2.0.dist-info/WHEEL
imobilebbs_slick_jiaocheng-2024.3.2.0.dist-info/entry_points.txt
imobilebbs_slick_jiaocheng-2024.3.2.0.dist-info/top_level.txt
imobilebbs_slick_jiaocheng-2024.3.2.0.dist-info/RECORD
